flake8_division.py
setup.py
flake8_future_division.egg-info/PKG-INFO
flake8_future_division.egg-info/SOURCES.txt
flake8_future_division.egg-info/dependency_links.txt
flake8_future_division.egg-info/entry_points.txt
flake8_future_division.egg-info/top_level.txt