Metadata-Version: 1.0
Name: flake8-future-division
Version: 0.1
Summary: A flake8 plugin to check for use of division without a __future__.division import
Home-page: https://github.com/Chronial/flake8-future-division
Author: Christian Fersch
Author-email: UNKNOWN
License: MIT
Platform: UNKNOWN
